sqil_core/__init__.py
sqil_core/config.py
sqil_core/config_log.py
sqil_core/experiment/__init__.py
sqil_core/experiment/_analysis.py
sqil_core/experiment/_events.py
sqil_core/experiment/_experiment.py
sqil_core/experiment/_utils.py
sqil_core/experiment/data/plottr.py
sqil_core/experiment/helpers/_function_override_handler.py
sqil_core/experiment/helpers/_labone_wrappers.py
sqil_core/experiment/instruments/__init__.py
sqil_core/experiment/instruments/_instrument.py
sqil_core/experiment/instruments/current_source.py
sqil_core/experiment/instruments/drivers/RohdeSchwarzZNB.py
sqil_core/experiment/instruments/drivers/SignalCore_SC5511A.py
sqil_core/experiment/instruments/drivers/Yokogawa_GS200.py
sqil_core/experiment/instruments/local_oscillator.py
sqil_core/experiment/instruments/rf_source.py
sqil_core/experiment/instruments/server.py
sqil_core/experiment/instruments/vna.py
sqil_core/experiment/instruments/zurich_instruments.py
sqil_core/fit/__init__.py
sqil_core/fit/_core.py
sqil_core/fit/_fit.py
sqil_core/fit/_guess.py
sqil_core/fit/_models.py
sqil_core/fit/_quality.py
sqil_core/resonator/__init__.py
sqil_core/resonator/_resonator.py
sqil_core/utils/__init__.py
sqil_core/utils/_analysis.py
sqil_core/utils/_const.py
sqil_core/utils/_formatter.py
sqil_core/utils/_plot.py
sqil_core/utils/_read.py
sqil_core/utils/_utils.py
sqil_core-2.0.0.dist-info/METADATA
sqil_core-2.0.0.dist-info/WHEEL
sqil_core-2.0.0.dist-info/entry_points.txt
sqil_core-2.0.0.dist-info/RECORD
