Metadata-Version: 2.4
Name: sqil-core
Version: 2.0.0
Summary: The codebase of the SQIL group in EPFL
Author: Andrea Duina
Requires-Python: >=3.12,<4.0
Classifier: Programming Language :: Python :: 3
Classifier: Programming Language :: Python :: 3.12
Classifier: Programming Language :: Python :: 3.13
Classifier: Programming Language :: Python :: 3.14
Requires-Dist: blinker (>=1.9.0,<2.0.0)
Requires-Dist: h5py (>=3.12.1,<4.0.0)
Requires-Dist: laboneq (>=25.10.3,<26.0.0)
Requires-Dist: laboneq-applications (>=25.10.0,<26.0.0)
Requires-Dist: lmfit (>=1.3.2,<2.0.0)
Requires-Dist: matplotlib (>=3.9.3,<4.0.0)
Requires-Dist: mpld3 (>=0.5.10,<0.6.0)
Requires-Dist: numpy (>=2.2.3,<3.0.0)
Requires-Dist: plottr (>=0.14.0,<0.15.0)
Requires-Dist: pyro5 (>=5.15,<6.0)
Requires-Dist: qcodes (>=0.51.0,<0.52.0)
Requires-Dist: qcodes-contrib-drivers (>=0.23.0,<0.24.0)
Requires-Dist: scipy (>=1.14.1,<2.0.0)
Requires-Dist: tabulate (>=0.9.0,<0.10.0)
Requires-Dist: tqdm (>=4.67.1,<5.0.0)
